ikuchnia/__init__.py
ikuchnia/meal_fetcher.py
ikuchnia/parse_html.py
ikuchnia/return_type.py
ikuchnia-0.0.1.dist-info/METADATA
ikuchnia-0.0.1.dist-info/WHEEL
ikuchnia-0.0.1.dist-info/top_level.txt
ikuchnia-0.0.1.dist-info/RECORD
