Metadata-Version: 2.1
Name: ikuchnia
Version: 0.0.1
Summary: Wrapper for iKuchnia api
Author: Mio-coder
Project-URL: Source, https://github.com/Mio-coder/ikuchnia_api
Project-URL: Homepage, https://github.com/Mio-coder/ikuchnia_api
Project-URL: Issues, https://github.com/Mio-coder/ikuchnia_api/issues
Classifier: Development Status :: 3 - Alpha
Classifier: Programming Language :: Python :: 3
Classifier: License :: OSI Approved :: MIT License
Classifier: Operating System :: OS Independent
Requires-Python: >=3.11
Requires-Dist: msgspec
Requires-Dist: requests
